cookiecutter_python_vscode_github/__init__.py
cookiecutter_python_vscode_github/__main__.py
cookiecutter_python_vscode_github/cookiecutter.json
cookiecutter_python_vscode_github/version.py
cookiecutter_python_vscode_github/{{cookiecutter.project_slug}}/.dockerignore
cookiecutter_python_vscode_github/{{cookiecutter.project_slug}}/.gitignore
cookiecutter_python_vscode_github/{{cookiecutter.project_slug}}/.pre-commit-config.yaml
cookiecutter_python_vscode_github/{{cookiecutter.project_slug}}/.pylintrc
cookiecutter_python_vscode_github/{{cookiecutter.project_slug}}/.shellcheckrc
cookiecutter_python_vscode_github/{{cookiecutter.project_slug}}/Makefile
cookiecutter_python_vscode_github/{{cookiecutter.project_slug}}/constraints.txt
cookiecutter_python_vscode_github/{{cookiecutter.project_slug}}/cookiecutter.yaml
cookiecutter_python_vscode_github/{{cookiecutter.project_slug}}/mypy.ini
cookiecutter_python_vscode_github/{{cookiecutter.project_slug}}/pyproject.toml
cookiecutter_python_vscode_github/{{cookiecutter.project_slug}}/requirements-dev.txt
cookiecutter_python_vscode_github/{{cookiecutter.project_slug}}/requirements-prod.txt
cookiecutter_python_vscode_github/{{cookiecutter.project_slug}}/.devcontainer/bash.sh
cookiecutter_python_vscode_github/{{cookiecutter.project_slug}}/.devcontainer/devcontainer.dockerfile
cookiecutter_python_vscode_github/{{cookiecutter.project_slug}}/.devcontainer/devcontainer.json
cookiecutter_python_vscode_github/{{cookiecutter.project_slug}}/.devcontainer/devcontainer.sh
cookiecutter_python_vscode_github/{{cookiecutter.project_slug}}/.github/workflows/makefile.yml
cookiecutter_python_vscode_github/{{cookiecutter.project_slug}}/.github/workflows/python-publish.yml
cookiecutter_python_vscode_github/{{cookiecutter.project_slug}}/.vscode/tasks.json
cookiecutter_python_vscode_github/{{cookiecutter.project_slug}}/tests/conftest.py
cookiecutter_python_vscode_github/{{cookiecutter.project_slug}}/tests/pytest.ini
cookiecutter_python_vscode_github-0.9.1.dist-info/LICENSE
cookiecutter_python_vscode_github-0.9.1.dist-info/METADATA
cookiecutter_python_vscode_github-0.9.1.dist-info/WHEEL
cookiecutter_python_vscode_github-0.9.1.dist-info/entry_points.txt
cookiecutter_python_vscode_github-0.9.1.dist-info/top_level.txt
cookiecutter_python_vscode_github-0.9.1.dist-info/RECORD
