Metadata-Version: 2.1
Name: cookiecutter-python-vscode-github
Version: 0.9.1
Summary: Cookiecutter Python VSCode GitHub provides a Python Package template with an IDE (Visual Studio Code) and a CI/CD (GitHub Actions) already setup.
Author-email: "Dinaldo A. Pessoa" <dinaldoap@gmail.com>
License: MIT License
Project-URL: repository, https://github.com/dinaldoap/cookiecutter-python-vscode-github
Classifier: Development Status :: 4 - Beta
Classifier: Programming Language :: Python :: 3
Requires-Python: >=3.8
License-File: LICENSE
